pylint_flask/__init__.py
pylint_flask-0.1.dist-info/DESCRIPTION.rst
pylint_flask-0.1.dist-info/METADATA
pylint_flask-0.1.dist-info/metadata.json
pylint_flask-0.1.dist-info/RECORD
pylint_flask-0.1.dist-info/top_level.txt
pylint_flask-0.1.dist-info/WHEEL
pylint_werkzeug/__init__.py
