Metadata-Version: 2.0
Name: pylint-flask
Version: 0.1
Summary: pylint-flask is a Pylint plugin to aid Pylint in recognising and understandingerrors caused when using Flask
Home-page: https://github.com/jschaf/pylint-flask
Author: Joe Schafer
Author-email: joe@jschaf.com
License: GPLv2
Keywords: pylint flask plugin
Platform: UNKNOWN
Classifier: Development Status :: 4 - Beta
Classifier: Environment :: Console
Classifier: Intended Audience :: Developers
Classifier: Operating System :: Unix
Classifier: Topic :: Software Development :: Quality Assurance
Classifier: Programming Language :: Python :: 2.7
Classifier: Programming Language :: Python :: 3.3
Classifier: Programming Language :: Python :: 3.4
Requires-Dist: pylint-plugin-utils (>=0.2.1)
Requires-Dist: pylint (>=1.0)
Requires-Dist: astroid (>=1.0)
Requires-Dist: logilab-common (>=0.60.0)
